[
  {
    "name": "ayuda",
    "path": "/ayuda",
    "component": "C:\\\\Users\\\\brisa\\\\Documents\\\\Brisa\\\\PlantillaSteelpro\\\\pages\\\\ayuda.vue",
    "chunkName": "pages/ayuda"
  },
  {
    "name": "inicio",
    "path": "/inicio",
    "component": "C:\\\\Users\\\\brisa\\\\Documents\\\\Brisa\\\\PlantillaSteelpro\\\\pages\\\\inicio.vue",
    "chunkName": "pages/inicio"
  },
  {
    "name": "tabla",
    "path": "/tabla",
    "component": "C:\\\\Users\\\\brisa\\\\Documents\\\\Brisa\\\\PlantillaSteelpro\\\\pages\\\\tabla.vue",
    "chunkName": "pages/tabla"
  },
  {
    "name": "actividades-actForaneas",
    "path": "/actividades/actForaneas",
    "component": "C:\\\\Users\\\\brisa\\\\Documents\\\\Brisa\\\\PlantillaSteelpro\\\\pages\\\\actividades\\\\actForaneas.vue",
    "chunkName": "pages/actividades/actForaneas"
  },
  {
    "name": "activos-activosFijos",
    "path": "/activos/activosFijos",
    "component": "C:\\\\Users\\\\brisa\\\\Documents\\\\Brisa\\\\PlantillaSteelpro\\\\pages\\\\activos\\\\activosFijos.vue",
    "chunkName": "pages/activos/activosFijos"
  },
  {
    "name": "activos-insumos",
    "path": "/activos/insumos",
    "component": "C:\\\\Users\\\\brisa\\\\Documents\\\\Brisa\\\\PlantillaSteelpro\\\\pages\\\\activos\\\\insumos.vue",
    "chunkName": "pages/activos/insumos"
  },
  {
    "name": "activos-mantenimiento",
    "path": "/activos/mantenimiento",
    "component": "C:\\\\Users\\\\brisa\\\\Documents\\\\Brisa\\\\PlantillaSteelpro\\\\pages\\\\activos\\\\mantenimiento.vue",
    "chunkName": "pages/activos/mantenimiento"
  },
  {
    "name": "activos-mostActmantt",
    "path": "/activos/mostActmantt",
    "component": "C:\\\\Users\\\\brisa\\\\Documents\\\\Brisa\\\\PlantillaSteelpro\\\\pages\\\\activos\\\\mostActmantt.vue",
    "chunkName": "pages/activos/mostActmantt"
  },
  {
    "name": "activos-mostmantt",
    "path": "/activos/mostmantt",
    "component": "C:\\\\Users\\\\brisa\\\\Documents\\\\Brisa\\\\PlantillaSteelpro\\\\pages\\\\activos\\\\mostmantt.vue",
    "chunkName": "pages/activos/mostmantt"
  },
  {
    "name": "activos-ubicacion",
    "path": "/activos/ubicacion",
    "component": "C:\\\\Users\\\\brisa\\\\Documents\\\\Brisa\\\\PlantillaSteelpro\\\\pages\\\\activos\\\\ubicacion.vue",
    "chunkName": "pages/activos/ubicacion"
  },
  {
    "name": "consumibles-consumible",
    "path": "/consumibles/consumible",
    "component": "C:\\\\Users\\\\brisa\\\\Documents\\\\Brisa\\\\PlantillaSteelpro\\\\pages\\\\consumibles\\\\consumible.vue",
    "chunkName": "pages/consumibles/consumible"
  },
  {
    "name": "preguntaSeg-formulario",
    "path": "/preguntaSeg/formulario",
    "component": "C:\\\\Users\\\\brisa\\\\Documents\\\\Brisa\\\\PlantillaSteelpro\\\\pages\\\\preguntaSeg\\\\formulario.vue",
    "chunkName": "pages/preguntaSeg/formulario"
  },
  {
    "name": "preguntaSeg-mostrarPreg",
    "path": "/preguntaSeg/mostrarPreg",
    "component": "C:\\\\Users\\\\brisa\\\\Documents\\\\Brisa\\\\PlantillaSteelpro\\\\pages\\\\preguntaSeg\\\\mostrarPreg.vue",
    "chunkName": "pages/preguntaSeg/mostrarPreg"
  },
  {
    "name": "SGI-ejejmplo",
    "path": "/SGI/ejejmplo",
    "component": "C:\\\\Users\\\\brisa\\\\Documents\\\\Brisa\\\\PlantillaSteelpro\\\\pages\\\\SGI\\\\ejejmplo.vue",
    "chunkName": "pages/SGI/ejejmplo"
  },
  {
    "name": "SGI-noconformidad",
    "path": "/SGI/noconformidad",
    "component": "C:\\\\Users\\\\brisa\\\\Documents\\\\Brisa\\\\PlantillaSteelpro\\\\pages\\\\SGI\\\\noconformidad.vue",
    "chunkName": "pages/SGI/noconformidad"
  },
  {
    "name": "socioscomerciales-proveedores",
    "path": "/socioscomerciales/proveedores",
    "component": "C:\\\\Users\\\\brisa\\\\Documents\\\\Brisa\\\\PlantillaSteelpro\\\\pages\\\\socioscomerciales\\\\proveedores.vue",
    "chunkName": "pages/socioscomerciales/proveedores"
  },
  {
    "name": "index",
    "path": "/",
    "component": "C:\\\\Users\\\\brisa\\\\Documents\\\\Brisa\\\\PlantillaSteelpro\\\\pages\\\\index.vue",
    "chunkName": "pages/index"
  }
]
